{
    "bottom": "",
    "trips": {
        "0": {
            "lat": 50.0468,
            "lon": 14.31741,
            "tripId": "904_4_220422",
            "route": "904",
            "routeType": 3,
            "bearing": 110,
            "delay": -4,
            "inactive": false,
            "statePosition": "on_track",
            "vehicle": "5078"
        },
        "1": {
            "lat": 50.02754,
            "lon": 14.50774,
            "tripId": "901_9_211129",
            "route": "901",
            "routeType": 3,
            "bearing": 164,
            "delay": 22,
            "inactive": false,
            "statePosition": "on_track",
            "vehicle": "3750"
        },
        "2": {
            "lat": 50.06833,
            "lon": 14.50671,
            "tripId": "906_14_211105",
            "route": "906",
            "routeType": 3,
            "bearing": null,
            "delay": 0,
            "inactive": true,
            "statePosition": "before_track",
            "vehicle": "3844"
        },
        "3": {
            "lat": 50.05306,
            "lon": 14.53728,
            "tripId": "911_94_220501",
            "route": "911",
            "routeType": 3,
            "bearing": 74,
            "delay": 0,
            "inactive": false,
            "statePosition": "on_track",
            "vehicle": "6890"
        },
        "4": {
            "lat": 50.11761,
            "lon": 14.46891,
            "tripId": "911_276_220419",
            "route": "911",
            "routeType": 3,
            "bearing": 20,
            "delay": 154,
            "inactive": false,
            "statePosition": "on_track",
            "vehicle": "6601"
        },
        "5": {
            "lat": 50.08208,
            "lon": 14.45941,
            "tripId": "913_70_220430",
            "route": "913",
            "routeType": 3,
            "bearing": 167,
            "delay": 46,
            "inactive": false,
            "statePosition": "on_track",
            "vehicle": "3680"
        },
        "6": {
            "lat": 50.05091,
            "lon": 14.40981,
            "tripId": "907_45_220430",
            "route": "907",
            "routeType": 3,
            "bearing": 338,
            "delay": 51,
            "inactive": false,
            "statePosition": "on_track",
            "vehicle": "3613"
        },
        "7": {
            "lat": 50.00905,
            "lon": 14.45558,
            "tripId": "904_22_220422",
            "route": "904",
            "routeType": 3,
            "bearing": 172,
            "delay": 58,
            "inactive": false,
            "statePosition": "on_track",
            "vehicle": "6637"
        },
        "8": {
            "lat": 50.13262,
            "lon": 14.42836,
            "tripId": "905_57_211031",
            "route": "905",
            "routeType": 3,
            "bearing": 202,
            "delay": 29,
            "inactive": false,
            "statePosition": "at_stop",
            "vehicle": "6889"
        },
        "9": {
            "lat": 50.11987,
            "lon": 14.48417,
            "tripId": "911_92_220501",
            "route": "911",
            "routeType": 3,
            "bearing": 28,
            "delay": 21,
            "inactive": false,
            "statePosition": "at_stop",
            "vehicle": "6739"
        },
        "10": {
            "lat": 50.08375,
            "lon": 14.43501,
            "tripId": "905_54_211031",
            "route": "905",
            "routeType": 3,
            "bearing": 205,
            "delay": 66,
            "inactive": false,
            "statePosition": "at_stop",
            "vehicle": "6893"
        },
        "11": {
            "lat": 50.08021,
            "lon": 14.37351,
            "tripId": "910_104_210604",
            "route": "910",
            "routeType": 3,
            "bearing": 87,
            "delay": -1,
            "inactive": false,
            "statePosition": "on_track",
            "vehicle": "6634"
        },
        "12": {
            "lat": 50.08835,
            "lon": 14.4325,
            "tripId": "907_6_220430",
            "route": "907",
            "routeType": 3,
            "bearing": 144,
            "delay": 195,
            "inactive": false,
            "statePosition": "at_stop",
            "vehicle": "3601"
        },
        "13": {
            "lat": 50.03524,
            "lon": 14.5162,
            "tripId": "905_51_211031",
            "route": "905",
            "routeType": 3,
            "bearing": 74,
            "delay": 49,
            "inactive": false,
            "statePosition": "on_track",
            "vehicle": "6798"
        },
        "14": {
            "lat": 50.004577042049,
            "lon": 14.403243802011,
            "tripId": "92_20_220430",
            "route": "92",
            "routeType": 0,
            "bearing": 347,
            "delay": 10,
            "inactive": false,
            "statePosition": "on_track",
            "vehicle": "8383"
        },
        "15": {
            "lat": 50.092925764432,
            "lon": 14.329800803466,
            "tripId": "91_158_211029",
            "route": "91",
            "routeType": 0,
            "bearing": 81,
            "delay": 11,
            "inactive": false,
            "statePosition": "at_stop",
            "vehicle": "8333"
        },
        "16": {
            "lat": 50.092971381702,
            "lon": 14.325351806974,
            "tripId": "91_162_220514",
            "route": "91",
            "routeType": 0,
            "bearing": 290,
            "delay": -205,
            "inactive": false,
            "statePosition": "at_stop",
            "vehicle": "8425"
        },
        "17": {
            "lat": 50.066862740507,
            "lon": 14.496046913136,
            "tripId": "99_337_220430",
            "route": "99",
            "routeType": 0,
            "bearing": 114,
            "delay": 9,
            "inactive": false,
            "statePosition": "at_stop",
            "vehicle": "8215"
        },
        "18": {
            "lat": 50.093943125442,
            "lon": 14.39001570329,
            "tripId": "97_461_220516",
            "route": "97",
            "routeType": 0,
            "bearing": 53,
            "delay": 51,
            "inactive": false,
            "statePosition": "on_track",
            "vehicle": "8441"
        },
        "19": {
            "lat": 50.049,
            "lon": 14.44286,
            "tripId": "910_111_220103",
            "route": "910",
            "routeType": 3,
            "bearing": 315,
            "delay": 41,
            "inactive": false,
            "statePosition": "on_track",
            "vehicle": "6656"
        },
        "20": {
            "lat": 50.07814,
            "lon": 14.41883,
            "tripId": "904_26_220422",
            "route": "904",
            "routeType": 3,
            "bearing": 63,
            "delay": 52,
            "inactive": false,
            "statePosition": "on_track",
            "vehicle": "6640"
        },
        "21": {
            "lat": 50.0535,
            "lon": 14.53646,
            "tripId": "911_282_220501",
            "route": "911",
            "routeType": 3,
            "bearing": null,
            "delay": 0,
            "inactive": true,
            "statePosition": "before_track",
            "vehicle": "6613"
        },
        "22": {
            "lat": 50.10554,
            "lon": 14.27176,
            "tripId": "907_14_220430",
            "route": "907",
            "routeType": 3,
            "bearing": null,
            "delay": 0,
            "inactive": true,
            "statePosition": "before_track",
            "vehicle": "3597"
        },
        "23": {
            "lat": 50.08715,
            "lon": 14.43535,
            "tripId": "905_79_211121",
            "route": "905",
            "routeType": 3,
            "bearing": 205,
            "delay": 78,
            "inactive": false,
            "statePosition": "on_track",
            "vehicle": "6909"
        },
        "24": {
            "lat": 50.10536,
            "lon": 14.27123,
            "tripId": "910_108_210604",
            "route": "910",
            "routeType": 3,
            "bearing": null,
            "delay": 0,
            "inactive": true,
            "statePosition": "before_track",
            "vehicle": "6715"
        },
        "25": {
            "lat": 50.03404,
            "lon": 14.48271,
            "tripId": "911_3_220320",
            "route": "911",
            "routeType": 3,
            "bearing": 117,
            "delay": 34,
            "inactive": false,
            "statePosition": "at_stop",
            "vehicle": "6608"
        },
        "26": {
            "lat": 50.04194,
            "lon": 14.3271,
            "tripId": "904_8_220422",
            "route": "904",
            "routeType": 3,
            "bearing": 329,
            "delay": 9,
            "inactive": false,
            "statePosition": "on_track",
            "vehicle": "6816"
        },
        "27": {
            "lat": 50.11086,
            "lon": 14.62433,
            "tripId": "912_21_210913",
            "route": "912",
            "routeType": 3,
            "bearing": null,
            "delay": 0,
            "inactive": true,
            "statePosition": "before_track",
            "vehicle": "3567"
        },
        "28": {
            "lat": 50.074983755339,
            "lon": 14.436090326719,
            "tripId": "97_458_220516",
            "route": "97",
            "routeType": 0,
            "bearing": 109,
            "delay": 15,
            "inactive": false,
            "statePosition": "at_stop",
            "vehicle": "8344"
        },
        "29": {
            "lat": 50.081428457279,
            "lon": 14.414065066154,
            "tripId": "99_341_220430",
            "route": "99",
            "routeType": 0,
            "bearing": 87,
            "delay": 12,
            "inactive": false,
            "statePosition": "at_stop",
            "vehicle": "8446"
        },
        "30": {
            "lat": 49.97276,
            "lon": 14.43166,
            "tripId": "913_76_220430",
            "route": "913",
            "routeType": 3,
            "bearing": null,
            "delay": 0,
            "inactive": true,
            "statePosition": "before_track",
            "vehicle": "3639"
        },
        "31": {
            "lat": 50.09074,
            "lon": 14.42781,
            "tripId": "909_184_220516",
            "route": "909",
            "routeType": 3,
            "bearing": 353,
            "delay": 35,
            "inactive": false,
            "statePosition": "on_track",
            "vehicle": "6616"
        },
        "32": {
            "lat": 50.08563,
            "lon": 14.51198,
            "tripId": "903_7_220503",
            "route": "903",
            "routeType": 3,
            "bearing": 60,
            "delay": 71,
            "inactive": false,
            "statePosition": "at_stop",
            "vehicle": "1862"
        },
        "33": {
            "lat": 50.0186,
            "lon": 14.51048,
            "tripId": "901_4_220422",
            "route": "901",
            "routeType": 3,
            "bearing": 330,
            "delay": 17,
            "inactive": false,
            "statePosition": "on_track",
            "vehicle": "3740"
        },
        "34": {
            "lat": 50.050581386761,
            "lon": 14.482078465704,
            "tripId": "96_90_220514",
            "route": "96",
            "routeType": 0,
            "bearing": null,
            "delay": 0,
            "inactive": true,
            "statePosition": "before_track",
            "vehicle": "8530"
        },
        "35": {
            "lat": 50.074869351339,
            "lon": 14.533062577082,
            "tripId": "95_798_220430",
            "route": "95",
            "routeType": 0,
            "bearing": null,
            "delay": 0,
            "inactive": true,
            "statePosition": "before_track_delayed",
            "vehicle": "8318"
        },
        "36": {
            "lat": 50.102457375998,
            "lon": 14.473333716729,
            "tripId": "90_94_220327",
            "route": "90",
            "routeType": 0,
            "bearing": null,
            "delay": 0,
            "inactive": true,
            "statePosition": "before_track",
            "vehicle": "8513"
        },
        "37": {
            "lat": 50.05444,
            "lon": 14.37033,
            "tripId": "908_291_220422",
            "route": "908",
            "routeType": 3,
            "bearing": null,
            "delay": 0,
            "inactive": true,
            "statePosition": "before_track",
            "vehicle": "3745"
        },
        "38": {
            "lat": 50.1426,
            "lon": 14.43088,
            "tripId": "905_78_211121",
            "route": "905",
            "routeType": 3,
            "bearing": 31,
            "delay": 30,
            "inactive": false,
            "statePosition": "at_stop",
            "vehicle": "6891"
        },
        "39": {
            "lat": 50.03329,
            "lon": 14.31192,
            "tripId": "902_4_210427",
            "route": "902",
            "routeType": 3,
            "bearing": 188,
            "delay": 10,
            "inactive": false,
            "statePosition": "at_stop",
            "vehicle": "4522"
        },
        "40": {
            "lat": 50.072569580858,
            "lon": 14.490447137105,
            "tripId": "91_145_211029",
            "route": "91",
            "routeType": 0,
            "bearing": 219,
            "delay": 13,
            "inactive": false,
            "statePosition": "on_track",
            "vehicle": "8332"
        },
        "41": {
            "lat": 50.075629333231,
            "lon": 14.323656147782,
            "tripId": "97_465_220516",
            "route": "97",
            "routeType": 0,
            "bearing": null,
            "delay": 0,
            "inactive": true,
            "statePosition": "before_track_delayed",
            "vehicle": "8419"
        },
        "42": {
            "lat": 50.07264,
            "lon": 14.68169,
            "tripId": "909_186_220516",
            "route": "909",
            "routeType": 3,
            "bearing": null,
            "delay": 0,
            "inactive": true,
            "statePosition": "before_track",
            "vehicle": "6765"
        },
        "43": {
            "lat": 50.13288,
            "lon": 14.51364,
            "tripId": "916_9_211207",
            "route": "916",
            "routeType": 3,
            "bearing": 183,
            "delay": 25,
            "inactive": false,
            "statePosition": "on_track",
            "vehicle": "3636"
        },
        "44": {
            "lat": 50.04825,
            "lon": 14.45775,
            "tripId": "910_116_210604",
            "route": "910",
            "routeType": 3,
            "bearing": 81,
            "delay": -20,
            "inactive": false,
            "statePosition": "at_stop",
            "vehicle": "6633"
        },
        "45": {
            "lat": 50.09154,
            "lon": 14.42763,
            "tripId": "909_178_220316",
            "route": "909",
            "routeType": 3,
            "bearing": 172,
            "delay": 3,
            "inactive": false,
            "statePosition": "on_track",
            "vehicle": "6789"
        },
        "46": {
            "lat": 50.074812325502,
            "lon": 14.53299349138,
            "tripId": "95_794_220430",
            "route": "95",
            "routeType": 0,
            "bearing": null,
            "delay": 0,
            "inactive": true,
            "statePosition": "before_track_delayed",
            "vehicle": "8528"
        },
        "47": {
            "lat": 50.087561766065,
            "lon": 14.432570640602,
            "tripId": "91_155_220514",
            "route": "91",
            "routeType": 0,
            "bearing": 0,
            "delay": -3,
            "inactive": false,
            "statePosition": "at_stop",
            "vehicle": "8417"
        },
        "48": {
            "lat": 50.004567583929,
            "lon": 14.403175135242,
            "tripId": "92_25_220430",
            "route": "92",
            "routeType": 0,
            "bearing": 166,
            "delay": -5,
            "inactive": false,
            "statePosition": "at_stop",
            "vehicle": "8476"
        },
        "49": {
            "lat": 50.10558,
            "lon": 14.2675,
            "tripId": "910_119_220103",
            "route": "910",
            "routeType": 3,
            "bearing": 126,
            "delay": 210,
            "inactive": false,
            "statePosition": "at_stop",
            "vehicle": "5065"
        },
        "50": {
            "lat": 49.99735,
            "lon": 14.42841,
            "tripId": "910_114_220103",
            "route": "910",
            "routeType": 3,
            "bearing": null,
            "delay": 0,
            "inactive": true,
            "statePosition": "before_track",
            "vehicle": "6635"
        },
        "51": {
            "lat": 49.99933,
            "lon": 14.61778,
            "tripId": "906_4_220420",
            "route": "906",
            "routeType": 3,
            "bearing": 215,
            "delay": 109,
            "inactive": false,
            "statePosition": "on_track",
            "vehicle": "3749"
        },
        "52": {
            "lat": 50.01986,
            "lon": 14.3542,
            "tripId": "951_20_220401",
            "route": "951",
            "routeType": 3,
            "bearing": 139,
            "delay": 113,
            "inactive": false,
            "statePosition": "on_track",
            "vehicle": "9826"
        },
        "53": {
            "lat": 50.15118,
            "lon": 14.43766,
            "tripId": "913_72_220430",
            "route": "913",
            "routeType": 3,
            "bearing": null,
            "delay": 0,
            "inactive": true,
            "statePosition": "before_track",
            "vehicle": "3677"
        },
        "54": {
            "lat": 50.06878,
            "lon": 14.40456,
            "tripId": "901_14_220422",
            "route": "901",
            "routeType": 3,
            "bearing": null,
            "delay": 0,
            "inactive": true,
            "statePosition": "before_track",
            "vehicle": "3748"
        },
        "55": {
            "lat": 50.03407,
            "lon": 14.48316,
            "tripId": "911_280_220501",
            "route": "911",
            "routeType": 3,
            "bearing": 291,
            "delay": 172,
            "inactive": false,
            "statePosition": "on_track",
            "vehicle": "6744"
        },
        "56": {
            "lat": 50.10704,
            "lon": 14.54739,
            "tripId": "912_10_210820",
            "route": "912",
            "routeType": 3,
            "bearing": null,
            "delay": 0,
            "inactive": true,
            "statePosition": "before_track",
            "vehicle": "3570"
        },
        "57": {
            "lat": 50.10712,
            "lon": 14.54761,
            "tripId": "953_113_220517",
            "route": "953",
            "routeType": 3,
            "bearing": 59,
            "delay": 0,
            "inactive": true,
            "statePosition": "before_track",
            "vehicle": "8223"
        },
        "58": {
            "lat": 50.106727453702,
            "lon": 14.547160016468,
            "tripId": "92_38_220430",
            "route": "92",
            "routeType": 0,
            "bearing": null,
            "delay": 0,
            "inactive": true,
            "statePosition": "before_track_delayed",
            "vehicle": "8452"
        },
        "59": {
            "lat": 50.088480663648,
            "lon": 14.415488001567,
            "tripId": "93_237_220425",
            "route": "93",
            "routeType": 0,
            "bearing": 14,
            "delay": 75,
            "inactive": false,
            "statePosition": "on_track",
            "vehicle": "8416"
        },
        "60": {
            "lat": 50.09818,
            "lon": 14.68681,
            "tripId": "908_306_220430",
            "route": "908",
            "routeType": 3,
            "bearing": null,
            "delay": 0,
            "inactive": true,
            "statePosition": "before_track",
            "vehicle": "3855"
        },
        "61": {
            "lat": 50.07036,
            "lon": 14.50942,
            "tripId": "908_303_220430",
            "route": "908",
            "routeType": 3,
            "bearing": 270,
            "delay": 45,
            "inactive": false,
            "statePosition": "on_track",
            "vehicle": "3572"
        },
        "62": {
            "lat": 50.07162648328,
            "lon": 14.486483659589,
            "tripId": "99_350_220430",
            "route": "99",
            "routeType": 0,
            "bearing": 247,
            "delay": 10,
            "inactive": false,
            "statePosition": "at_stop",
            "vehicle": "8455"
        },
        "63": {
            "lat": 50.01369,
            "lon": 14.45264,
            "tripId": "904_18_220422",
            "route": "904",
            "routeType": 3,
            "bearing": 332,
            "delay": 42,
            "inactive": false,
            "statePosition": "on_track",
            "vehicle": "6636"
        },
        "64": {
            "lat": 50.065471873945,
            "lon": 14.298098507582,
            "tripId": "99_321_220430",
            "route": "99",
            "routeType": 0,
            "bearing": null,
            "delay": 0,
            "inactive": true,
            "statePosition": "before_track",
            "vehicle": "8457"
        },
        "65": {
            "lat": 50.132671121451,
            "lon": 14.453760664905,
            "tripId": "90_105_220327",
            "route": "90",
            "routeType": 0,
            "bearing": null,
            "delay": 0,
            "inactive": true,
            "statePosition": "before_track_delayed",
            "vehicle": "8563"
        },
        "66": {
            "lat": 50.086583786764,
            "lon": 14.339767065647,
            "tripId": "96_30_211201",
            "route": "96",
            "routeType": 0,
            "bearing": null,
            "delay": 0,
            "inactive": true,
            "statePosition": "before_track",
            "vehicle": "8245"
        },
        "67": {
            "lat": 50.106813259515,
            "lon": 14.547126509132,
            "tripId": "92_6_220430",
            "route": "92",
            "routeType": 0,
            "bearing": null,
            "delay": 0,
            "inactive": true,
            "statePosition": "before_track_delayed",
            "vehicle": "8510"
        },
        "68": {
            "lat": 50.00646,
            "lon": 14.6137,
            "tripId": "906_9_211105",
            "route": "906",
            "routeType": 3,
            "bearing": 181,
            "delay": 318,
            "inactive": false,
            "statePosition": "on_track",
            "vehicle": "3741"
        },
        "69": {
            "lat": 50.077186264847,
            "lon": 14.48553806189,
            "tripId": "91_141_220514",
            "route": "91",
            "routeType": 0,
            "bearing": 280,
            "delay": 26,
            "inactive": false,
            "statePosition": "at_stop",
            "vehicle": "8310"
        },
        "70": {
            "lat": 50.16492,
            "lon": 14.48478,
            "tripId": "914_9_220228",
            "route": "914",
            "routeType": 3,
            "bearing": 84,
            "delay": 0,
            "inactive": true,
            "statePosition": "before_track",
            "vehicle": "8195"
        },
        "71": {
            "lat": 50.08663,
            "lon": 14.45556,
            "tripId": "913_74_220430",
            "route": "913",
            "routeType": 3,
            "bearing": 0,
            "delay": 180,
            "inactive": false,
            "statePosition": "on_track",
            "vehicle": "3682"
        },
        "72": {
            "lat": 49.99826,
            "lon": 14.16187,
            "tripId": "952_29_210901",
            "route": "952",
            "routeType": 3,
            "bearing": 227,
            "delay": 166,
            "inactive": false,
            "statePosition": "on_track",
            "vehicle": "9970"
        },
        "73": {
            "lat": 50.065475820349,
            "lon": 14.298088938235,
            "tripId": "99_325_220430",
            "route": "99",
            "routeType": 0,
            "bearing": null,
            "delay": 0,
            "inactive": true,
            "statePosition": "before_track",
            "vehicle": "8368"
        },
        "74": {
            "lat": 50.0816597356,
            "lon": 14.425259510795,
            "tripId": "98_37_220429",
            "route": "98",
            "routeType": 0,
            "bearing": 217,
            "delay": 11,
            "inactive": false,
            "statePosition": "on_track",
            "vehicle": "8229"
        },
        "75": {
            "lat": 50.097345516548,
            "lon": 14.404900826397,
            "tripId": "96_23_210930",
            "route": "96",
            "routeType": 0,
            "bearing": 74,
            "delay": 55,
            "inactive": false,
            "statePosition": "on_track",
            "vehicle": "8331"
        },
        "76": {
            "lat": 50.10568,
            "lon": 14.27183,
            "tripId": "907_43_220430",
            "route": "907",
            "routeType": 3,
            "bearing": 10,
            "delay": 37,
            "inactive": false,
            "statePosition": "on_track",
            "vehicle": "3598"
        },
        "77": {
            "lat": 50.07252,
            "lon": 14.40803,
            "tripId": "904_44_220422",
            "route": "904",
            "routeType": 3,
            "bearing": 264,
            "delay": 19,
            "inactive": false,
            "statePosition": "at_stop",
            "vehicle": "6823"
        },
        "78": {
            "lat": 50.065890946858,
            "lon": 14.325714786816,
            "tripId": "98_63_220429",
            "route": "98",
            "routeType": 0,
            "bearing": 233,
            "delay": 19,
            "inactive": false,
            "statePosition": "on_track",
            "vehicle": "8237"
        },
        "79": {
            "lat": 50.132060641972,
            "lon": 14.479387671238,
            "tripId": "93_553_220425",
            "route": "93",
            "routeType": 0,
            "bearing": null,
            "delay": 0,
            "inactive": true,
            "statePosition": "before_track",
            "vehicle": "8432"
        },
        "80": {
            "lat": 50.07007,
            "lon": 14.53744,
            "tripId": "908_286_220422",
            "route": "908",
            "routeType": 3,
            "bearing": 8,
            "delay": 68,
            "inactive": false,
            "statePosition": "on_track",
            "vehicle": "3736"
        },
        "81": {
            "lat": 50.068031163321,
            "lon": 14.345414466939,
            "tripId": "98_620_220516",
            "route": "98",
            "routeType": 0,
            "bearing": 87,
            "delay": 41,
            "inactive": false,
            "statePosition": "at_stop",
            "vehicle": "8447"
        },
        "82": {
            "lat": 50.03415,
            "lon": 14.50913,
            "tripId": "905_80_211121",
            "route": "905",
            "routeType": 3,
            "bearing": 266,
            "delay": 32,
            "inactive": false,
            "statePosition": "on_track",
            "vehicle": "6885"
        },
        "83": {
            "lat": 50.075363681984,
            "lon": 14.43163079063,
            "tripId": "96_16_210930",
            "route": "96",
            "routeType": 0,
            "bearing": 96,
            "delay": 44,
            "inactive": false,
            "statePosition": "on_track",
            "vehicle": "8233"
        },
        "84": {
            "lat": 50.132784546829,
            "lon": 14.47970649356,
            "tripId": "93_559_220425",
            "route": "93",
            "routeType": 0,
            "bearing": null,
            "delay": 0,
            "inactive": true,
            "statePosition": "before_track",
            "vehicle": "8477"
        },
        "85": {
            "lat": 50.091866092107,
            "lon": 14.498528935469,
            "tripId": "95_829_220514",
            "route": "95",
            "routeType": 0,
            "bearing": null,
            "delay": 0,
            "inactive": true,
            "statePosition": "before_track",
            "vehicle": "8436"
        },
        "86": {
            "lat": 50.031552300335,
            "lon": 14.367837523516,
            "tripId": "94_47_220411",
            "route": "94",
            "routeType": 0,
            "bearing": null,
            "delay": 0,
            "inactive": true,
            "statePosition": "before_track",
            "vehicle": "8479"
        },
        "87": {
            "lat": 50.093865310396,
            "lon": 14.389755838887,
            "tripId": "96_82_220514",
            "route": "96",
            "routeType": 0,
            "bearing": 243,
            "delay": -9,
            "inactive": false,
            "statePosition": "at_stop",
            "vehicle": "8433"
        },
        "88": {
            "lat": 50.15127,
            "lon": 14.59016,
            "tripId": "953_115_220517",
            "route": "953",
            "routeType": 3,
            "bearing": 44,
            "delay": 650,
            "inactive": false,
            "statePosition": "on_track",
            "vehicle": "8144"
        },
        "89": {
            "lat": 50.072475986135,
            "lon": 14.407893618524,
            "tripId": "94_13_220411",
            "route": "94",
            "routeType": 0,
            "bearing": 262,
            "delay": -42,
            "inactive": false,
            "statePosition": "at_stop",
            "vehicle": "8498"
        },
        "90": {
            "lat": 50.103296475094,
            "lon": 14.452976179642,
            "tripId": "94_29_220411",
            "route": "94",
            "routeType": 0,
            "bearing": 90,
            "delay": 50,
            "inactive": false,
            "statePosition": "at_stop",
            "vehicle": "8464"
        },
        "91": {
            "lat": 50.057010077829,
            "lon": 14.438082825605,
            "tripId": "93_233_220425",
            "route": "93",
            "routeType": 0,
            "bearing": null,
            "delay": 0,
            "inactive": true,
            "statePosition": "before_track_delayed",
            "vehicle": "8327"
        },
        "92": {
            "lat": 50.065463408937,
            "lon": 14.298002176672,
            "tripId": "98_622_220516",
            "route": "98",
            "routeType": 0,
            "bearing": null,
            "delay": 0,
            "inactive": true,
            "statePosition": "before_track",
            "vehicle": "8450"
        },
        "93": {
            "lat": 50.106721609657,
            "lon": 14.547231647041,
            "tripId": "94_36_220411",
            "route": "94",
            "routeType": 0,
            "bearing": null,
            "delay": 0,
            "inactive": true,
            "statePosition": "before_track_delayed",
            "vehicle": "8550"
        },
        "94": {
            "lat": 50.087574349167,
            "lon": 14.432540185842,
            "tripId": "92_13_220430",
            "route": "92",
            "routeType": 0,
            "bearing": 358,
            "delay": 0,
            "inactive": false,
            "statePosition": "at_stop",
            "vehicle": "8449"
        },
        "95": {
            "lat": 50.031492256109,
            "lon": 14.367821705851,
            "tripId": "94_6_220411",
            "route": "94",
            "routeType": 0,
            "bearing": null,
            "delay": 0,
            "inactive": true,
            "statePosition": "before_track",
            "vehicle": "8488"
        },
        "96": {
            "lat": 50.03457,
            "lon": 14.53856,
            "tripId": "905_81_211121",
            "route": "905",
            "routeType": 3,
            "bearing": null,
            "delay": 0,
            "inactive": true,
            "statePosition": "before_track",
            "vehicle": "6745"
        },
        "97": {
            "lat": 50.090624926908,
            "lon": 14.385599696509,
            "tripId": "97_468_220516",
            "route": "97",
            "routeType": 0,
            "bearing": 157,
            "delay": 192,
            "inactive": false,
            "statePosition": "at_stop",
            "vehicle": "8227"
        },
        "98": {
            "lat": 50.057068840773,
            "lon": 14.438184152382,
            "tripId": "93_556_220425",
            "route": "93",
            "routeType": 0,
            "bearing": 251,
            "delay": 90,
            "inactive": false,
            "statePosition": "at_stop",
            "vehicle": "8489"
        },
        "99": {
            "lat": 50.12695,
            "lon": 14.36679,
            "tripId": "902_12_210427",
            "route": "902",
            "routeType": 3,
            "bearing": null,
            "delay": 0,
            "inactive": true,
            "statePosition": "before_track",
            "vehicle": "4532"
        },
        "100": {
            "lat": 50.081436229559,
            "lon": 14.41410290856,
            "tripId": "93_557_220425",
            "route": "93",
            "routeType": 0,
            "bearing": 87,
            "delay": 18,
            "inactive": false,
            "statePosition": "at_stop",
            "vehicle": "8495"
        },
        "101": {
            "lat": 50.07709947074,
            "lon": 14.419505130857,
            "tripId": "94_41_220411",
            "route": "94",
            "routeType": 0,
            "bearing": 0,
            "delay": -19,
            "inactive": false,
            "statePosition": "at_stop",
            "vehicle": "8467"
        },
        "102": {
            "lat": 50.092158534185,
            "lon": 14.480976628933,
            "tripId": "95_808_220430",
            "route": "95",
            "routeType": 0,
            "bearing": 82,
            "delay": 100,
            "inactive": false,
            "statePosition": "on_track",
            "vehicle": "8365"
        },
        "103": {
            "lat": 50.075657227631,
            "lon": 14.42245973638,
            "tripId": "97_472_220516",
            "route": "97",
            "routeType": 0,
            "bearing": 270,
            "delay": 7,
            "inactive": false,
            "statePosition": "on_track",
            "vehicle": "8320"
        },
        "104": {
            "lat": 50.068713513954,
            "lon": 14.42044304775,
            "tripId": "95_827_220514",
            "route": "95",
            "routeType": 0,
            "bearing": 158,
            "delay": 27,
            "inactive": false,
            "statePosition": "on_track",
            "vehicle": "8389"
        },
        "105": {
            "lat": 50.087501423059,
            "lon": 14.432448270801,
            "tripId": "92_31_220430",
            "route": "92",
            "routeType": 0,
            "bearing": 188,
            "delay": 110,
            "inactive": false,
            "statePosition": "on_track",
            "vehicle": "8505"
        },
        "106": {
            "lat": 50.053125227102,
            "lon": 14.536788361238,
            "tripId": "97_476_220516",
            "route": "97",
            "routeType": 0,
            "bearing": null,
            "delay": 0,
            "inactive": true,
            "statePosition": "before_track_delayed",
            "vehicle": "8465"
        },
        "107": {
            "lat": 50.053122693005,
            "lon": 14.536829587294,
            "tripId": "97_455_220516",
            "route": "97",
            "routeType": 0,
            "bearing": 55,
            "delay": 97,
            "inactive": false,
            "statePosition": "at_stop",
            "vehicle": "8309"
        },
        "108": {
            "lat": 50.074721440737,
            "lon": 14.418982318141,
            "tripId": "95_812_220430",
            "route": "95",
            "routeType": 0,
            "bearing": 8,
            "delay": -6,
            "inactive": false,
            "statePosition": "at_stop",
            "vehicle": "8360"
        },
        "109": {
            "lat": 50.085984601834,
            "lon": 14.435117377289,
            "tripId": "98_628_220516",
            "route": "98",
            "routeType": 0,
            "bearing": 119,
            "delay": 29,
            "inactive": false,
            "statePosition": "at_stop",
            "vehicle": "8456"
        },
        "110": {
            "lat": 50.087520838329,
            "lon": 14.432401013615,
            "tripId": "91_150_211029",
            "route": "91",
            "routeType": 0,
            "bearing": 188,
            "delay": 82,
            "inactive": false,
            "statePosition": "on_track",
            "vehicle": "8330"
        },
        "111": {
            "lat": 50.075464551971,
            "lon": 14.431439709964,
            "tripId": "96_86_220514",
            "route": "96",
            "routeType": 0,
            "bearing": 272,
            "delay": 56,
            "inactive": false,
            "statePosition": "at_stop",
            "vehicle": "8415"
        },
        "112": {
            "lat": 50.10239,
            "lon": 14.47349,
            "tripId": "895_233_220327",
            "route": "X95",
            "routeType": 3,
            "bearing": 175,
            "delay": 24,
            "inactive": false,
            "statePosition": "on_track",
            "vehicle": "3548"
        },
        "113": {
            "lat": 50.091509155751,
            "lon": 14.499343370652,
            "tripId": "98_10_220429",
            "route": "98",
            "routeType": 0,
            "bearing": null,
            "delay": 0,
            "inactive": true,
            "statePosition": "before_track",
            "vehicle": "8384"
        },
        "114": {
            "lat": 50.107781117271,
            "lon": 14.447048708443,
            "tripId": "94_21_220411",
            "route": "94",
            "routeType": 0,
            "bearing": 291,
            "delay": 59,
            "inactive": false,
            "statePosition": "on_track",
            "vehicle": "8444"
        },
        "115": {
            "lat": 50.08011,
            "lon": 14.36816,
            "tripId": "910_100_220103",
            "route": "910",
            "routeType": 3,
            "bearing": 268,
            "delay": 23,
            "inactive": false,
            "statePosition": "on_track",
            "vehicle": "6733"
        },
        "116": {
            "lat": 50.10028,
            "lon": 14.48714,
            "tripId": "895_265_220414",
            "route": "X95",
            "routeType": 3,
            "bearing": 82,
            "delay": 108,
            "inactive": false,
            "statePosition": "on_track",
            "vehicle": "3541"
        },
        "117": {
            "lat": 50.078502821818,
            "lon": 14.404144633851,
            "tripId": "99_347_220430",
            "route": "99",
            "routeType": 0,
            "bearing": 175,
            "delay": 49,
            "inactive": false,
            "statePosition": "at_stop",
            "vehicle": "8351"
        }
    }
}