{
    "bottom": "",
    "alert": "",
    "trips": {
        "0": {
            "lat": 49.93343,
            "lon": 14.42283,
            "tripId": "445_57_220901",
            "route": "445",
            "routeType": 3,
            "bearing": 150,
            "delay": 0,
            "inactive": true,
            "statePosition": "before_track",
            "vehicle": "1105"
        },
        "1": {
            "lat": 50.08856,
            "lon": 14.66591,
            "tripId": "221_669_220211",
            "route": "221",
            "routeType": 3,
            "bearing": 19,
            "delay": 102,
            "inactive": false,
            "statePosition": "on_track",
            "vehicle": "1752"
        },
        "2": {
            "lat": 50.06616,
            "lon": 14.5991,
            "tripId": "240_251_221102",
            "route": "240",
            "routeType": 3,
            "bearing": 28,
            "delay": 129,
            "inactive": false,
            "statePosition": "on_track",
            "vehicle": "1763"
        },
        "3": {
            "lat": 49.99183,
            "lon": 14.69225,
            "tripId": "959_17_230305",
            "route": "959",
            "routeType": 3,
            "bearing": 295,
            "delay": 537,
            "inactive": false,
            "statePosition": "on_track",
            "vehicle": "1816"
        },
        "4": {
            "lat": 50.08535,
            "lon": 14.51142,
            "tripId": "903_42_220901",
            "route": "903",
            "routeType": 3,
            "bearing": 58,
            "delay": -28,
            "inactive": false,
            "statePosition": "at_stop",
            "vehicle": "1862"
        },
        "5": {
            "lat": 50.0246,
            "lon": 14.62167,
            "tripId": "382_383_220901",
            "route": "382",
            "routeType": 3,
            "bearing": 131,
            "delay": 45,
            "inactive": false,
            "statePosition": "on_track",
            "vehicle": "1885"
        },
        "6": {
            "lat": 49.93349,
            "lon": 14.42281,
            "tripId": "333_229_220904",
            "route": "333",
            "routeType": 3,
            "bearing": 141,
            "delay": -33,
            "inactive": false,
            "statePosition": "at_stop",
            "vehicle": "1992"
        },
        "7": {
            "lat": 50.06189,
            "lon": 14.47033,
            "tripId": "101_1563_221112",
            "route": "101",
            "routeType": 3,
            "bearing": null,
            "delay": 0,
            "inactive": true,
            "statePosition": "before_track",
            "vehicle": "2320"
        },
        "8": {
            "lat": 50.12112,
            "lon": 14.51201,
            "tripId": "159_407_230315",
            "route": "159",
            "routeType": 3,
            "bearing": null,
            "delay": 0,
            "inactive": true,
            "statePosition": "before_track",
            "vehicle": "2331"
        },
        "9": {
            "lat": 50.10578,
            "lon": 14.2676,
            "tripId": "907_39_221027",
            "route": "907",
            "routeType": 3,
            "bearing": 131,
            "delay": 54,
            "inactive": false,
            "statePosition": "on_track",
            "vehicle": "3595"
        },
        "10": {
            "lat": 50.10555,
            "lon": 14.27173,
            "tripId": "907_165_221112",
            "route": "907",
            "routeType": 3,
            "bearing": null,
            "delay": 0,
            "inactive": true,
            "statePosition": "before_track",
            "vehicle": "3599"
        },
        "11": {
            "lat": 50.0418,
            "lon": 14.40732,
            "tripId": "907_160_221027",
            "route": "907",
            "routeType": 3,
            "bearing": 15,
            "delay": 36,
            "inactive": false,
            "statePosition": "on_track",
            "vehicle": "3616"
        },
        "12": {
            "lat": 50.08319,
            "lon": 14.46371,
            "tripId": "913_69_221211",
            "route": "913",
            "routeType": 3,
            "bearing": 277,
            "delay": 142,
            "inactive": false,
            "statePosition": "on_track",
            "vehicle": "3676"
        },
        "13": {
            "lat": 50.07584,
            "lon": 14.30372,
            "tripId": "340_164_210901",
            "route": "340",
            "routeType": 3,
            "bearing": null,
            "delay": 0,
            "inactive": true,
            "statePosition": "before_track",
            "vehicle": "3687"
        },
        "14": {
            "lat": 50.06018,
            "lon": 14.41063,
            "tripId": "901_53_221026",
            "route": "901",
            "routeType": 3,
            "bearing": 306,
            "delay": 58,
            "inactive": false,
            "statePosition": "on_track",
            "vehicle": "3736"
        },
        "15": {
            "lat": 50.05445,
            "lon": 14.37026,
            "tripId": "908_204_221201",
            "route": "908",
            "routeType": 3,
            "bearing": null,
            "delay": 0,
            "inactive": true,
            "statePosition": "before_track",
            "vehicle": "3740"
        },
        "16": {
            "lat": 50.06387,
            "lon": 14.52636,
            "tripId": "908_201_230114",
            "route": "908",
            "routeType": 3,
            "bearing": 331,
            "delay": 36,
            "inactive": false,
            "statePosition": "on_track",
            "vehicle": "3743"
        },
        "17": {
            "lat": 50.08107,
            "lon": 14.66179,
            "tripId": "908_206_230114",
            "route": "908",
            "routeType": 3,
            "bearing": null,
            "delay": 0,
            "inactive": true,
            "statePosition": "before_track",
            "vehicle": "3748"
        },
        "18": {
            "lat": 50.00305,
            "lon": 14.61401,
            "tripId": "906_68_210715",
            "route": "906",
            "routeType": 3,
            "bearing": 156,
            "delay": 54,
            "inactive": false,
            "statePosition": "on_track",
            "vehicle": "3749"
        },
        "19": {
            "lat": 50.02627,
            "lon": 14.40403,
            "tripId": "892_329_230401",
            "route": "X92",
            "routeType": 3,
            "bearing": 179,
            "delay": 95,
            "inactive": false,
            "statePosition": "on_track",
            "vehicle": "4044"
        },
        "20": {
            "lat": 50.12597,
            "lon": 14.37227,
            "tripId": "902_9_221021",
            "route": "902",
            "routeType": 3,
            "bearing": 277,
            "delay": 275,
            "inactive": false,
            "statePosition": "at_stop",
            "vehicle": "4532"
        },
        "21": {
            "lat": 50.13578,
            "lon": 14.28025,
            "tripId": "312_198_221027",
            "route": "312",
            "routeType": 3,
            "bearing": 358,
            "delay": 306,
            "inactive": false,
            "statePosition": "at_stop",
            "vehicle": "4542"
        },
        "22": {
            "lat": 50.05019,
            "lon": 14.44081,
            "tripId": "910_403_230401",
            "route": "910",
            "routeType": 3,
            "bearing": 147,
            "delay": 183,
            "inactive": false,
            "statePosition": "on_track",
            "vehicle": "5078"
        },
        "23": {
            "lat": 50.10014,
            "lon": 14.44326,
            "tripId": "911_87_221210",
            "route": "911",
            "routeType": 3,
            "bearing": 2,
            "delay": 475,
            "inactive": false,
            "statePosition": "on_track",
            "vehicle": "6601"
        },
        "24": {
            "lat": 50.03408,
            "lon": 14.48313,
            "tripId": "911_113_220901",
            "route": "911",
            "routeType": 3,
            "bearing": 291,
            "delay": 126,
            "inactive": false,
            "statePosition": "on_track",
            "vehicle": "6609"
        },
        "25": {
            "lat": 50.01335,
            "lon": 14.45772,
            "tripId": "904_216_230116",
            "route": "904",
            "routeType": 3,
            "bearing": 254,
            "delay": 11,
            "inactive": false,
            "statePosition": "on_track",
            "vehicle": "6640"
        },
        "26": {
            "lat": 50.0486,
            "lon": 14.45967,
            "tripId": "910_398_230201",
            "route": "910",
            "routeType": 3,
            "bearing": 264,
            "delay": 148,
            "inactive": false,
            "statePosition": "on_track",
            "vehicle": "6643"
        },
        "27": {
            "lat": 50.07406,
            "lon": 14.38936,
            "tripId": "910_395_230201",
            "route": "910",
            "routeType": 3,
            "bearing": 36,
            "delay": 405,
            "inactive": false,
            "statePosition": "on_track",
            "vehicle": "6644"
        },
        "28": {
            "lat": 50.07715,
            "lon": 14.42601,
            "tripId": "904_214_230116",
            "route": "904",
            "routeType": 3,
            "bearing": 273,
            "delay": 198,
            "inactive": false,
            "statePosition": "on_track",
            "vehicle": "6663"
        },
        "29": {
            "lat": 50.0342,
            "lon": 14.51111,
            "tripId": "905_68_230401",
            "route": "905",
            "routeType": 3,
            "bearing": 81,
            "delay": 13,
            "inactive": false,
            "statePosition": "on_track",
            "vehicle": "6823"
        },
        "30": {
            "lat": 50.0399,
            "lon": 14.46554,
            "tripId": "196_541_221126",
            "route": "196",
            "routeType": 3,
            "bearing": null,
            "delay": 0,
            "inactive": true,
            "statePosition": "before_track",
            "vehicle": "6841"
        },
        "31": {
            "lat": 50.11762,
            "lon": 14.46893,
            "tripId": "911_342_230227",
            "route": "911",
            "routeType": 3,
            "bearing": 20,
            "delay": 56,
            "inactive": false,
            "statePosition": "on_track",
            "vehicle": "6882"
        },
        "32": {
            "lat": 50.16886,
            "lon": 14.19545,
            "tripId": "342_224_221031",
            "route": "342",
            "routeType": 3,
            "bearing": 301,
            "delay": 353,
            "inactive": false,
            "statePosition": "on_track",
            "vehicle": "7716"
        },
        "33": {
            "lat": 50.19492,
            "lon": 14.56064,
            "tripId": "377_1016_230411",
            "route": "377",
            "routeType": 3,
            "bearing": 301,
            "delay": 28,
            "inactive": false,
            "statePosition": "on_track",
            "vehicle": "8023"
        },
        "34": {
            "lat": 50.18985,
            "lon": 14.66758,
            "tripId": "375_1053_220901",
            "route": "375",
            "routeType": 3,
            "bearing": 26,
            "delay": 319,
            "inactive": false,
            "statePosition": "at_stop",
            "vehicle": "8225"
        },
        "35": {
            "lat": 50.092338780848,
            "lon": 14.331211116549,
            "tripId": "91_1000_230407",
            "route": "91",
            "routeType": 0,
            "bearing": null,
            "delay": 0,
            "inactive": true,
            "statePosition": "before_track",
            "vehicle": "8278"
        },
        "36": {
            "lat": 50.084982559797,
            "lon": 14.430144222458,
            "tripId": "92_1095_230414",
            "route": "92",
            "routeType": 0,
            "bearing": 56,
            "delay": 46,
            "inactive": false,
            "statePosition": "at_stop",
            "vehicle": "8507"
        },
        "37": {
            "lat": 50.15985,
            "lon": 14.33172,
            "tripId": "350_255_230407",
            "route": "350",
            "routeType": 3,
            "bearing": 63,
            "delay": 104,
            "inactive": false,
            "statePosition": "on_track",
            "vehicle": "8766"
        },
        "38": {
            "lat": 50.08955,
            "lon": 14.21478,
            "tripId": "306_639_210901",
            "route": "306",
            "routeType": 3,
            "bearing": 341,
            "delay": -37,
            "inactive": false,
            "statePosition": "at_stop",
            "vehicle": "8881"
        },
        "39": {
            "lat": 50.13007,
            "lon": 14.23778,
            "tripId": "322_536_221211",
            "route": "322",
            "routeType": 3,
            "bearing": 318,
            "delay": 34,
            "inactive": false,
            "statePosition": "on_track",
            "vehicle": "8887"
        },
        "40": {
            "lat": 50.0833,
            "lon": 14.24426,
            "tripId": "365_323_221212",
            "route": "365",
            "routeType": 3,
            "bearing": 264,
            "delay": -11,
            "inactive": false,
            "statePosition": "on_track",
            "vehicle": "8938"
        },
        "41": {
            "lat": 50.14069,
            "lon": 14.23664,
            "tripId": "324_785_220901",
            "route": "324",
            "routeType": 3,
            "bearing": 304,
            "delay": 75,
            "inactive": false,
            "statePosition": "on_track",
            "vehicle": "8965"
        },
        "42": {
            "lat": 50.0941,
            "lon": 14.7174,
            "tripId": "344_130_211212",
            "route": "344",
            "routeType": 3,
            "bearing": 46,
            "delay": -37,
            "inactive": false,
            "statePosition": "on_track",
            "vehicle": "9106"
        },
        "43": {
            "lat": 50.07438,
            "lon": 14.67029,
            "tripId": "163_330_220813",
            "route": "163",
            "routeType": 3,
            "bearing": 106,
            "delay": 221,
            "inactive": false,
            "statePosition": "on_track",
            "vehicle": "9121"
        },
        "44": {
            "lat": 49.95524,
            "lon": 14.48389,
            "tripId": "960_40_220901",
            "route": "960",
            "routeType": 3,
            "bearing": 263,
            "delay": 0,
            "inactive": true,
            "statePosition": "before_track",
            "vehicle": "9161"
        },
        "45": {
            "lat": 49.96969,
            "lon": 14.53394,
            "tripId": "327_158_221211",
            "route": "327",
            "routeType": 3,
            "bearing": 259,
            "delay": 224,
            "inactive": false,
            "statePosition": "on_track",
            "vehicle": "9395"
        },
        "46": {
            "lat": 49.71864,
            "lon": 14.32993,
            "tripId": "360_391_230327",
            "route": "360",
            "routeType": 3,
            "bearing": 225,
            "delay": 8,
            "inactive": false,
            "statePosition": "at_stop",
            "vehicle": "9559"
        },
        "47": {
            "lat": 49.85224,
            "lon": 14.40437,
            "tripId": "338_357_230327",
            "route": "338",
            "routeType": 3,
            "bearing": 341,
            "delay": -23,
            "inactive": false,
            "statePosition": "on_track",
            "vehicle": "9743"
        },
        "48": {
            "lat": 50.03391,
            "lon": 14.23152,
            "tripId": "952_27_230401",
            "route": "952",
            "routeType": 3,
            "bearing": 239,
            "delay": 292,
            "inactive": false,
            "statePosition": "at_stop",
            "vehicle": "9771"
        },
        "49": {
            "lat": 49.7817,
            "lon": 14.17065,
            "tripId": "395_955_230313",
            "route": "395",
            "routeType": 3,
            "bearing": 221,
            "delay": -98,
            "inactive": false,
            "statePosition": "on_track",
            "vehicle": "9880"
        },
        "50": {
            "lat": 49.91006,
            "lon": 14.49448,
            "tripId": "332_668_221216",
            "route": "332",
            "routeType": 3,
            "bearing": 212,
            "delay": 117,
            "inactive": false,
            "statePosition": "on_track",
            "vehicle": "9926"
        },
        "51": {
            "lat": 49.92315,
            "lon": 14.57506,
            "tripId": "339_127_221211",
            "route": "339",
            "routeType": 3,
            "bearing": 131,
            "delay": 329,
            "inactive": false,
            "statePosition": "at_stop",
            "vehicle": "9936"
        },
        "52": {
            "lat": 50.25545,
            "lon": 14.5212,
            "tripId": "348_366_220228",
            "route": "348",
            "routeType": 3,
            "bearing": 12,
            "delay": 97,
            "inactive": false,
            "statePosition": "on_track",
            "vehicle": "9946"
        },
        "53": {
            "lat": 50.04358,
            "lon": 14.44063,
            "tripId": "956_4_230401",
            "route": "956",
            "routeType": 3,
            "bearing": 270,
            "delay": 0,
            "inactive": true,
            "statePosition": "before_track",
            "vehicle": "9954"
        },
        "54": {
            "lat": 50.00504,
            "lon": 14.40431,
            "tripId": "917_34_230328",
            "route": "917",
            "routeType": 3,
            "bearing": 55,
            "delay": 89,
            "inactive": false,
            "statePosition": "at_stop",
            "vehicle": "1759"
        },
        "55": {
            "lat": 49.99197,
            "lon": 14.34653,
            "tripId": "120_972_230320",
            "route": "120",
            "routeType": 3,
            "bearing": 127,
            "delay": 134,
            "inactive": false,
            "statePosition": "on_track",
            "vehicle": "3607"
        },
        "56": {
            "lat": 50.12094,
            "lon": 14.51041,
            "tripId": "810_3132_220414",
            "route": "X10",
            "routeType": 3,
            "bearing": null,
            "delay": 0,
            "inactive": true,
            "statePosition": "before_track",
            "vehicle": "3977"
        },
        "57": {
            "lat": 50.03262,
            "lon": 14.3123,
            "tripId": "902_3_221021",
            "route": "902",
            "routeType": 3,
            "bearing": null,
            "delay": 0,
            "inactive": true,
            "statePosition": "before_track",
            "vehicle": "4526"
        },
        "58": {
            "lat": 50.03562,
            "lon": 14.51728,
            "tripId": "905_84_220720",
            "route": "905",
            "routeType": 3,
            "bearing": 253,
            "delay": 17,
            "inactive": false,
            "statePosition": "at_stop",
            "vehicle": "5065"
        },
        "59": {
            "lat": 50.04042,
            "lon": 14.46533,
            "tripId": "188_1050_211126",
            "route": "188",
            "routeType": 3,
            "bearing": null,
            "delay": 0,
            "inactive": true,
            "statePosition": "before_track",
            "vehicle": "5074"
        },
        "60": {
            "lat": 50.05347,
            "lon": 14.53668,
            "tripId": "911_337_230227",
            "route": "911",
            "routeType": 3,
            "bearing": null,
            "delay": 0,
            "inactive": true,
            "statePosition": "before_track",
            "vehicle": "6623"
        },
        "61": {
            "lat": 50.04,
            "lon": 14.46539,
            "tripId": "193_3074_230401",
            "route": "193",
            "routeType": 3,
            "bearing": null,
            "delay": 0,
            "inactive": true,
            "statePosition": "before_track",
            "vehicle": "6703"
        },
        "62": {
            "lat": 50.13265,
            "lon": 14.42973,
            "tripId": "905_213_220801",
            "route": "905",
            "routeType": 3,
            "bearing": 6,
            "delay": 101,
            "inactive": false,
            "statePosition": "on_track",
            "vehicle": "6739"
        },
        "63": {
            "lat": 50.07901,
            "lon": 14.43247,
            "tripId": "905_82_220720",
            "route": "905",
            "routeType": 3,
            "bearing": 46,
            "delay": 177,
            "inactive": false,
            "statePosition": "on_track",
            "vehicle": "6744"
        },
        "64": {
            "lat": 50.01194,
            "lon": 14.41673,
            "tripId": "910_133_210715",
            "route": "910",
            "routeType": 3,
            "bearing": 205,
            "delay": 87,
            "inactive": false,
            "statePosition": "on_track",
            "vehicle": "6896"
        },
        "65": {
            "lat": 50.050538259244,
            "lon": 14.481994311512,
            "tripId": "96_676_230201",
            "route": "96",
            "routeType": 0,
            "bearing": null,
            "delay": 0,
            "inactive": true,
            "statePosition": "before_track",
            "vehicle": "8343"
        },
        "66": {
            "lat": 50.07767061129,
            "lon": 14.480412292011,
            "tripId": "91_993_230407",
            "route": "91",
            "routeType": 0,
            "bearing": 98,
            "delay": 102,
            "inactive": false,
            "statePosition": "at_stop",
            "vehicle": "8442"
        },
        "67": {
            "lat": 50.1574,
            "lon": 14.31609,
            "tripId": "954_1_210904",
            "route": "954",
            "routeType": 3,
            "bearing": 323,
            "delay": 0,
            "inactive": true,
            "statePosition": "before_track",
            "vehicle": "8855"
        },
        "68": {
            "lat": 49.95437,
            "lon": 14.44311,
            "tripId": "331_317_230306",
            "route": "331",
            "routeType": 3,
            "bearing": 237,
            "delay": 14,
            "inactive": false,
            "statePosition": "on_track",
            "vehicle": "9137"
        },
        "69": {
            "lat": 50.112096141386,
            "lon": 14.475335339985,
            "tripId": "14_11025_230313",
            "route": "14",
            "routeType": 0,
            "bearing": 38,
            "delay": -2,
            "inactive": false,
            "statePosition": "at_stop",
            "vehicle": "9271"
        },
        "70": {
            "lat": 50.071974159726,
            "lon": 14.402765300339,
            "tripId": "12_2485_230327",
            "route": "12",
            "routeType": 0,
            "bearing": 263,
            "delay": 45,
            "inactive": false,
            "statePosition": "on_track",
            "vehicle": "9390"
        },
        "71": {
            "lat": 50.01716,
            "lon": 14.34958,
            "tripId": "951_58_230320",
            "route": "951",
            "routeType": 3,
            "bearing": 359,
            "delay": 184,
            "inactive": false,
            "statePosition": "on_track",
            "vehicle": "9460"
        },
        "72": {
            "lat": 50.13287,
            "lon": 14.51364,
            "tripId": "916_5_230325",
            "route": "916",
            "routeType": 3,
            "bearing": 183,
            "delay": -25,
            "inactive": false,
            "statePosition": "on_track",
            "vehicle": "2338"
        },
        "73": {
            "lat": 50.10696,
            "lon": 14.54719,
            "tripId": "912_6_220921",
            "route": "912",
            "routeType": 3,
            "bearing": null,
            "delay": 0,
            "inactive": true,
            "statePosition": "before_track",
            "vehicle": "3571"
        },
        "74": {
            "lat": 50.00238,
            "lon": 14.41122,
            "tripId": "892_325_230401",
            "route": "X92",
            "routeType": 3,
            "bearing": 267,
            "delay": 41,
            "inactive": false,
            "statePosition": "on_track",
            "vehicle": "4051"
        },
        "75": {
            "lat": 50.04,
            "lon": 14.47887,
            "tripId": "911_339_230227",
            "route": "911",
            "routeType": 3,
            "bearing": 82,
            "delay": 71,
            "inactive": false,
            "statePosition": "on_track",
            "vehicle": "6677"
        },
        "76": {
            "lat": 50.067650655427,
            "lon": 14.336563904503,
            "tripId": "98_367_230326",
            "route": "98",
            "routeType": 0,
            "bearing": 85,
            "delay": 33,
            "inactive": false,
            "statePosition": "on_track",
            "vehicle": "8312"
        },
        "77": {
            "lat": 50.068444117643,
            "lon": 14.492654053587,
            "tripId": "99_353_220704",
            "route": "99",
            "routeType": 0,
            "bearing": 311,
            "delay": 7,
            "inactive": false,
            "statePosition": "on_track",
            "vehicle": "8453"
        },
        "78": {
            "lat": 50.081631219692,
            "lon": 14.425378905525,
            "tripId": "98_365_230326",
            "route": "98",
            "routeType": 0,
            "bearing": 36,
            "delay": 76,
            "inactive": false,
            "statePosition": "at_stop",
            "vehicle": "8464"
        },
        "79": {
            "lat": 50.122487330694,
            "lon": 14.455959171428,
            "tripId": "93_1017_230414",
            "route": "93",
            "routeType": 0,
            "bearing": 358,
            "delay": 191,
            "inactive": false,
            "statePosition": "at_stop",
            "vehicle": "8523"
        },
        "80": {
            "lat": 50.09246700962,
            "lon": 14.484975699686,
            "tripId": "95_1016_221204",
            "route": "95",
            "routeType": 0,
            "bearing": 90,
            "delay": 64,
            "inactive": false,
            "statePosition": "at_stop",
            "vehicle": "8545"
        },
        "81": {
            "lat": 50.08272,
            "lon": 14.50664,
            "tripId": "908_199_221201",
            "route": "908",
            "routeType": 3,
            "bearing": 76,
            "delay": 129,
            "inactive": false,
            "statePosition": "on_track",
            "vehicle": "3527"
        },
        "82": {
            "lat": 50.08845,
            "lon": 14.43253,
            "tripId": "907_150_221112",
            "route": "907",
            "routeType": 3,
            "bearing": 178,
            "delay": 81,
            "inactive": false,
            "statePosition": "on_track",
            "vehicle": "3594"
        },
        "83": {
            "lat": 50.08418,
            "lon": 14.4571,
            "tripId": "913_73_220901",
            "route": "913",
            "routeType": 3,
            "bearing": 142,
            "delay": -3,
            "inactive": false,
            "statePosition": "on_track",
            "vehicle": "3637"
        },
        "84": {
            "lat": 49.9845,
            "lon": 14.58632,
            "tripId": "363_226_220608",
            "route": "363",
            "routeType": 3,
            "bearing": 215,
            "delay": 52,
            "inactive": false,
            "statePosition": "on_track",
            "vehicle": "3670"
        },
        "85": {
            "lat": 50.10022,
            "lon": 14.48682,
            "tripId": "895_263_221204",
            "route": "X95",
            "routeType": 3,
            "bearing": 81,
            "delay": 95,
            "inactive": false,
            "statePosition": "at_stop",
            "vehicle": "3732"
        },
        "86": {
            "lat": 50.03726,
            "lon": 14.50883,
            "tripId": "901_158_230103",
            "route": "901",
            "routeType": 3,
            "bearing": 198,
            "delay": 12,
            "inactive": false,
            "statePosition": "on_track",
            "vehicle": "3741"
        },
        "87": {
            "lat": 50.10418,
            "lon": 14.47562,
            "tripId": "895_229_221204",
            "route": "X95",
            "routeType": 3,
            "bearing": 244,
            "delay": 4,
            "inactive": false,
            "statePosition": "on_track",
            "vehicle": "3814"
        },
        "88": {
            "lat": 49.99931,
            "lon": 14.61777,
            "tripId": "906_8_220720",
            "route": "906",
            "routeType": 3,
            "bearing": 215,
            "delay": 21,
            "inactive": false,
            "statePosition": "on_track",
            "vehicle": "3855"
        },
        "89": {
            "lat": 50.09897,
            "lon": 14.422,
            "tripId": "909_101_221201",
            "route": "909",
            "routeType": 3,
            "bearing": 162,
            "delay": 49,
            "inactive": false,
            "statePosition": "on_track",
            "vehicle": "6669"
        },
        "90": {
            "lat": 50.08768,
            "lon": 14.43259,
            "tripId": "905_62_230401",
            "route": "905",
            "routeType": 3,
            "bearing": 144,
            "delay": 65,
            "inactive": false,
            "statePosition": "at_stop",
            "vehicle": "6912"
        },
        "91": {
            "lat": 50.0131,
            "lon": 14.45284,
            "tripId": "904_331_230401",
            "route": "904",
            "routeType": 3,
            "bearing": 152,
            "delay": 38,
            "inactive": false,
            "statePosition": "at_stop",
            "vehicle": "6923"
        },
        "92": {
            "lat": 50.031463785992,
            "lon": 14.366525652446,
            "tripId": "94_1060_230414",
            "route": "94",
            "routeType": 0,
            "bearing": null,
            "delay": 0,
            "inactive": true,
            "statePosition": "before_track",
            "vehicle": "8255"
        },
        "93": {
            "lat": 50.06802,
            "lon": 14.50718,
            "tripId": "906_3_220720",
            "route": "906",
            "routeType": 3,
            "bearing": null,
            "delay": 0,
            "inactive": true,
            "statePosition": "before_track",
            "vehicle": "3746"
        },
        "94": {
            "lat": 50.04095,
            "lon": 14.33461,
            "tripId": "904_81_210715",
            "route": "904",
            "routeType": 3,
            "bearing": 281,
            "delay": 155,
            "inactive": false,
            "statePosition": "on_track",
            "vehicle": "6645"
        },
        "95": {
            "lat": 50.085018330962,
            "lon": 14.445210863398,
            "tripId": "98_47_230326",
            "route": "98",
            "routeType": 0,
            "bearing": 281,
            "delay": 148,
            "inactive": false,
            "statePosition": "at_stop",
            "vehicle": "8458"
        },
        "96": {
            "lat": 50.08684,
            "lon": 14.66548,
            "tripId": "211_400_221211",
            "route": "211",
            "routeType": 3,
            "bearing": 49,
            "delay": 0,
            "inactive": true,
            "statePosition": "before_track",
            "vehicle": "9338"
        },
        "97": {
            "lat": 50.065475376048,
            "lon": 14.298048863065,
            "tripId": "98_369_230326",
            "route": "98",
            "routeType": 0,
            "bearing": null,
            "delay": 0,
            "inactive": true,
            "statePosition": "before_track",
            "vehicle": "8229"
        },
        "98": {
            "lat": 50.093839642985,
            "lon": 14.389770734535,
            "tripId": "97_759_230326",
            "route": "97",
            "routeType": 0,
            "bearing": 236,
            "delay": 198,
            "inactive": false,
            "statePosition": "at_stop",
            "vehicle": "8467"
        },
        "99": {
            "lat": 50.088251668572,
            "lon": 14.432478786686,
            "tripId": "91_997_230407",
            "route": "91",
            "routeType": 0,
            "bearing": 188,
            "delay": 3,
            "inactive": false,
            "statePosition": "at_stop",
            "vehicle": "8527"
        },
        "100": {
            "lat": 50.10686526979,
            "lon": 14.547235275465,
            "tripId": "14_11098_230313",
            "route": "14",
            "routeType": 0,
            "bearing": 244,
            "delay": 9,
            "inactive": false,
            "statePosition": "on_track",
            "vehicle": "9144"
        },
        "101": {
            "lat": 50.091524763086,
            "lon": 14.499455783071,
            "tripId": "98_53_230326",
            "route": "98",
            "routeType": 0,
            "bearing": null,
            "delay": 0,
            "inactive": true,
            "statePosition": "before_track",
            "vehicle": "8465"
        },
        "102": {
            "lat": 50.07259,
            "lon": 14.40757,
            "tripId": "904_333_230401",
            "route": "904",
            "routeType": 3,
            "bearing": 83,
            "delay": 101,
            "inactive": false,
            "statePosition": "at_stop",
            "vehicle": "6816"
        },
        "103": {
            "lat": 50.11409,
            "lon": 14.28644,
            "tripId": "910_393_230401",
            "route": "910",
            "routeType": 3,
            "bearing": null,
            "delay": 0,
            "inactive": true,
            "statePosition": "before_track",
            "vehicle": "6933"
        },
        "104": {
            "lat": 50.07551298496,
            "lon": 14.431473072722,
            "tripId": "97_762_230326",
            "route": "97",
            "routeType": 0,
            "bearing": 272,
            "delay": 23,
            "inactive": false,
            "statePosition": "at_stop",
            "vehicle": "8342"
        },
        "105": {
            "lat": 50.081180175495,
            "lon": 14.406091360101,
            "tripId": "99_351_220704",
            "route": "99",
            "routeType": 0,
            "bearing": 270,
            "delay": 16,
            "inactive": false,
            "statePosition": "at_stop",
            "vehicle": "8305"
        },
        "106": {
            "lat": 50.106852424289,
            "lon": 14.547624807445,
            "tripId": "92_1090_230401",
            "route": "92",
            "routeType": 0,
            "bearing": null,
            "delay": 0,
            "inactive": true,
            "statePosition": "before_track",
            "vehicle": "8282"
        },
        "107": {
            "lat": 50.067208462381,
            "lon": 14.421620268062,
            "tripId": "95_1018_221204",
            "route": "95",
            "routeType": 0,
            "bearing": 339,
            "delay": 6,
            "inactive": false,
            "statePosition": "on_track",
            "vehicle": "8309"
        },
        "108": {
            "lat": 50.099539951318,
            "lon": 14.395607935124,
            "tripId": "22_16540_230327",
            "route": "22",
            "routeType": 0,
            "bearing": 349,
            "delay": 40,
            "inactive": false,
            "statePosition": "at_stop",
            "vehicle": "9323"
        },
        "109": {
            "lat": 50.074865390208,
            "lon": 14.533096559547,
            "tripId": "95_1020_221204",
            "route": "95",
            "routeType": 0,
            "bearing": null,
            "delay": 0,
            "inactive": true,
            "statePosition": "before_track",
            "vehicle": "8243"
        },
        "110": {
            "lat": 49.9924,
            "lon": 14.83151,
            "tripId": "381_139_220901",
            "route": "381",
            "routeType": 3,
            "bearing": 91,
            "delay": 572,
            "inactive": false,
            "statePosition": "on_track",
            "vehicle": "1882"
        },
        "111": {
            "lat": 50.22761,
            "lon": 14.4164,
            "tripId": "373_114_221201",
            "route": "373",
            "routeType": 3,
            "bearing": 135,
            "delay": 92,
            "inactive": false,
            "statePosition": "on_track",
            "vehicle": "8035"
        },
        "112": {
            "lat": 50.084964564678,
            "lon": 14.430187242893,
            "tripId": "91_1007_230201",
            "route": "91",
            "routeType": 0,
            "bearing": 56,
            "delay": 27,
            "inactive": false,
            "statePosition": "at_stop",
            "vehicle": "8338"
        },
        "113": {
            "lat": 50.081700475936,
            "lon": 14.404469383146,
            "tripId": "93_1011_230414",
            "route": "93",
            "routeType": 0,
            "bearing": 175,
            "delay": 74,
            "inactive": false,
            "statePosition": "on_track",
            "vehicle": "8379"
        },
        "114": {
            "lat": 50.072807862288,
            "lon": 14.43337423421,
            "tripId": "96_683_230201",
            "route": "96",
            "routeType": 0,
            "bearing": 346,
            "delay": -24,
            "inactive": false,
            "statePosition": "at_stop",
            "vehicle": "8516"
        },
        "115": {
            "lat": 50.099718489638,
            "lon": 14.42105953858,
            "tripId": "96_681_230201",
            "route": "96",
            "routeType": 0,
            "bearing": 256,
            "delay": 268,
            "inactive": false,
            "statePosition": "at_stop",
            "vehicle": "8530"
        },
        "116": {
            "lat": 50.125934201931,
            "lon": 14.45984638252,
            "tripId": "93_1014_230414",
            "route": "93",
            "routeType": 0,
            "bearing": 257,
            "delay": -7,
            "inactive": false,
            "statePosition": "at_stop",
            "vehicle": "8384"
        },
        "117": {
            "lat": 50.096781691729,
            "lon": 14.352245218202,
            "tripId": "91_1003_230201",
            "route": "91",
            "routeType": 0,
            "bearing": 255,
            "delay": 265,
            "inactive": false,
            "statePosition": "on_track",
            "vehicle": "8316"
        },
        "118": {
            "lat": 50.0801,
            "lon": 14.36951,
            "tripId": "910_388_230401",
            "route": "910",
            "routeType": 3,
            "bearing": 89,
            "delay": 68,
            "inactive": false,
            "statePosition": "on_track",
            "vehicle": "6719"
        },
        "119": {
            "lat": 50.064554391599,
            "lon": 14.308479290279,
            "tripId": "99_673_221216",
            "route": "99",
            "routeType": 0,
            "bearing": null,
            "delay": 0,
            "inactive": true,
            "statePosition": "before_track",
            "vehicle": "8472"
        },
        "120": {
            "lat": 50.09211,
            "lon": 14.42733,
            "tripId": "909_124_230114",
            "route": "909",
            "routeType": 3,
            "bearing": 351,
            "delay": 78,
            "inactive": false,
            "statePosition": "on_track",
            "vehicle": "6765"
        },
        "121": {
            "lat": 50.081410496996,
            "lon": 14.414510077211,
            "tripId": "93_1020_230414",
            "route": "93",
            "routeType": 0,
            "bearing": 270,
            "delay": 23,
            "inactive": false,
            "statePosition": "at_stop",
            "vehicle": "8388"
        },
        "122": {
            "lat": 50.070475161666,
            "lon": 14.488692149592,
            "tripId": "99_669_221216",
            "route": "99",
            "routeType": 0,
            "bearing": 138,
            "delay": -3,
            "inactive": false,
            "statePosition": "at_stop",
            "vehicle": "8454"
        },
        "123": {
            "lat": 50.065439896844,
            "lon": 14.298060719021,
            "tripId": "99_666_221216",
            "route": "99",
            "routeType": 0,
            "bearing": null,
            "delay": 0,
            "inactive": true,
            "statePosition": "before_track",
            "vehicle": "8468"
        },
        "124": {
            "lat": 50.04668,
            "lon": 14.31641,
            "tripId": "904_335_230401",
            "route": "904",
            "routeType": 3,
            "bearing": null,
            "delay": 0,
            "inactive": true,
            "statePosition": "before_track",
            "vehicle": "6820"
        },
        "125": {
            "lat": 50.106194390541,
            "lon": 14.472656743802,
            "tripId": "90_89_221204",
            "route": "90",
            "routeType": 0,
            "bearing": 173,
            "delay": -1,
            "inactive": false,
            "statePosition": "at_stop",
            "vehicle": "8399"
        },
        "126": {
            "lat": 50.087512798642,
            "lon": 14.432428849772,
            "tripId": "92_1077_230401",
            "route": "92",
            "routeType": 0,
            "bearing": 188,
            "delay": 90,
            "inactive": false,
            "statePosition": "on_track",
            "vehicle": "8473"
        },
        "127": {
            "lat": 50.053100842786,
            "lon": 14.536860449515,
            "tripId": "97_765_230327",
            "route": "97",
            "routeType": 0,
            "bearing": null,
            "delay": 0,
            "inactive": true,
            "statePosition": "before_track",
            "vehicle": "8176"
        },
        "128": {
            "lat": 50.056254145808,
            "lon": 14.441349650848,
            "tripId": "93_1006_230414",
            "route": "93",
            "routeType": 0,
            "bearing": 7,
            "delay": 158,
            "inactive": false,
            "statePosition": "at_stop",
            "vehicle": "8180"
        },
        "129": {
            "lat": 50.132630389618,
            "lon": 14.453707135918,
            "tripId": "90_101_221204",
            "route": "90",
            "routeType": 0,
            "bearing": null,
            "delay": 0,
            "inactive": true,
            "statePosition": "before_track",
            "vehicle": "8181"
        },
        "130": {
            "lat": 50.106799566504,
            "lon": 14.547146418483,
            "tripId": "94_1039_230414",
            "route": "94",
            "routeType": 0,
            "bearing": null,
            "delay": 0,
            "inactive": true,
            "statePosition": "before_track",
            "vehicle": "8302"
        },
        "131": {
            "lat": 50.059154867462,
            "lon": 14.420181138802,
            "tripId": "92_1074_230401",
            "route": "92",
            "routeType": 0,
            "bearing": null,
            "delay": 0,
            "inactive": true,
            "statePosition": "before_track",
            "vehicle": "8324"
        },
        "132": {
            "lat": 50.053060891359,
            "lon": 14.536833532496,
            "tripId": "97_758_230326",
            "route": "97",
            "routeType": 0,
            "bearing": null,
            "delay": 0,
            "inactive": true,
            "statePosition": "before_track",
            "vehicle": "8414"
        },
        "133": {
            "lat": 50.14085,
            "lon": 14.43066,
            "tripId": "905_66_230401",
            "route": "905",
            "routeType": 3,
            "bearing": 180,
            "delay": 74,
            "inactive": false,
            "statePosition": "on_track",
            "vehicle": "6745"
        },
        "134": {
            "lat": 50.28655,
            "lon": 14.84037,
            "tripId": "345_186_230410",
            "route": "345",
            "routeType": 3,
            "bearing": 33,
            "delay": 251,
            "inactive": false,
            "statePosition": "on_track",
            "vehicle": "9536"
        },
        "135": {
            "lat": 50.073252267357,
            "lon": 14.415323477933,
            "tripId": "94_1041_230414",
            "route": "94",
            "routeType": 0,
            "bearing": 249,
            "delay": 9,
            "inactive": false,
            "statePosition": "at_stop",
            "vehicle": "8457"
        },
        "136": {
            "lat": 50.075456556663,
            "lon": 14.430849406325,
            "tripId": "97_781_230326",
            "route": "97",
            "routeType": 0,
            "bearing": 93,
            "delay": -38,
            "inactive": false,
            "statePosition": "at_stop",
            "vehicle": "8559"
        },
        "137": {
            "lat": 50.098291267476,
            "lon": 14.444183903852,
            "tripId": "94_1047_230414",
            "route": "94",
            "routeType": 0,
            "bearing": 93,
            "delay": 296,
            "inactive": false,
            "statePosition": "at_stop",
            "vehicle": "8495"
        },
        "138": {
            "lat": 50.0755858739,
            "lon": 14.423273412378,
            "tripId": "96_28_230213",
            "route": "96",
            "routeType": 0,
            "bearing": 93,
            "delay": 67,
            "inactive": false,
            "statePosition": "on_track",
            "vehicle": "8234"
        },
        "139": {
            "lat": 50.16515,
            "lon": 14.48498,
            "tripId": "914_5_220228",
            "route": "914",
            "routeType": 3,
            "bearing": 262,
            "delay": 0,
            "inactive": true,
            "statePosition": "before_track",
            "vehicle": "8050"
        },
        "140": {
            "lat": 50.057099918438,
            "lon": 14.438101261529,
            "tripId": "93_1024_230414",
            "route": "93",
            "routeType": 0,
            "bearing": null,
            "delay": 0,
            "inactive": true,
            "statePosition": "before_track",
            "vehicle": "8489"
        },
        "141": {
            "lat": 50.103454524207,
            "lon": 14.46563986582,
            "tripId": "94_1044_230414",
            "route": "94",
            "routeType": 0,
            "bearing": 268,
            "delay": 18,
            "inactive": false,
            "statePosition": "at_stop",
            "vehicle": "8449"
        },
        "142": {
            "lat": 50.097197015737,
            "lon": 14.40394015131,
            "tripId": "96_34_230213",
            "route": "96",
            "routeType": 0,
            "bearing": 90,
            "delay": -32,
            "inactive": false,
            "statePosition": "at_stop",
            "vehicle": "8386"
        },
        "143": {
            "lat": 50.074565914049,
            "lon": 14.418922839836,
            "tripId": "95_830_230321",
            "route": "95",
            "routeType": 0,
            "bearing": 190,
            "delay": 47,
            "inactive": false,
            "statePosition": "at_stop",
            "vehicle": "8360"
        },
        "144": {
            "lat": 50.090200466842,
            "lon": 14.38586718727,
            "tripId": "97_783_230326",
            "route": "97",
            "routeType": 0,
            "bearing": 0,
            "delay": 38,
            "inactive": false,
            "statePosition": "at_stop",
            "vehicle": "8533"
        },
        "145": {
            "lat": 50.074813127269,
            "lon": 14.533105572658,
            "tripId": "95_1022_221204",
            "route": "95",
            "routeType": 0,
            "bearing": null,
            "delay": 0,
            "inactive": true,
            "statePosition": "before_track",
            "vehicle": "8430"
        },
        "146": {
            "lat": 50.075153762948,
            "lon": 14.489988377757,
            "tripId": "91_1009_230201",
            "route": "91",
            "routeType": 0,
            "bearing": 338,
            "delay": -20,
            "inactive": false,
            "statePosition": "at_stop",
            "vehicle": "8323"
        },
        "147": {
            "lat": 50.072358190995,
            "lon": 14.407253132595,
            "tripId": "94_1051_230414",
            "route": "94",
            "routeType": 0,
            "bearing": 84,
            "delay": 89,
            "inactive": false,
            "statePosition": "at_stop",
            "vehicle": "8482"
        },
        "148": {
            "lat": 50.075702967045,
            "lon": 14.404078486719,
            "tripId": "99_671_221216",
            "route": "99",
            "routeType": 0,
            "bearing": 5,
            "delay": 108,
            "inactive": false,
            "statePosition": "at_stop",
            "vehicle": "8351"
        },
        "149": {
            "lat": 50.086643455563,
            "lon": 14.339799240954,
            "tripId": "96_3_230213",
            "route": "96",
            "routeType": 0,
            "bearing": null,
            "delay": 0,
            "inactive": true,
            "statePosition": "before_track",
            "vehicle": "8419"
        },
        "150": {
            "lat": 50.067869080513,
            "lon": 14.341480683861,
            "tripId": "98_41_230326",
            "route": "98",
            "routeType": 0,
            "bearing": 266,
            "delay": 46,
            "inactive": false,
            "statePosition": "at_stop",
            "vehicle": "8420"
        },
        "151": {
            "lat": 50.031364803754,
            "lon": 14.367514910614,
            "tripId": "94_1055_230414",
            "route": "94",
            "routeType": 0,
            "bearing": null,
            "delay": 0,
            "inactive": true,
            "statePosition": "before_track",
            "vehicle": "8480"
        },
        "152": {
            "lat": 50.075544769631,
            "lon": 14.322834551014,
            "tripId": "97_786_230326",
            "route": "97",
            "routeType": 0,
            "bearing": null,
            "delay": 0,
            "inactive": true,
            "statePosition": "before_track",
            "vehicle": "8448"
        },
        "153": {
            "lat": 50.091854338809,
            "lon": 14.498633541505,
            "tripId": "95_832_230321",
            "route": "95",
            "routeType": 0,
            "bearing": null,
            "delay": 0,
            "inactive": true,
            "statePosition": "before_track",
            "vehicle": "8350"
        },
        "154": {
            "lat": 49.8220329,
            "lon": 13.7788267,
            "tripId": "1216_750_221211",
            "route": "R16",
            "routeType": 2,
            "bearing": 198,
            "delay": 0,
            "inactive": false,
            "statePosition": "at_stop",
            "vehicle": "750"
        },
        "155": {
            "lat": 49.66759,
            "lon": 14.624444,
            "tripId": "1217_737_221211",
            "route": "R17",
            "routeType": 2,
            "bearing": 186,
            "delay": -16,
            "inactive": true,
            "statePosition": "at_stop",
            "vehicle": "737"
        },
        "156": {
            "lat": 50.2292023,
            "lon": 14.8816891,
            "tripId": "1322_9439_221211",
            "route": "S22",
            "routeType": 2,
            "bearing": 24,
            "delay": 57,
            "inactive": false,
            "statePosition": "at_stop",
            "vehicle": "9439"
        },
        "157": {
            "lat": 50.1120834,
            "lon": 14.5692129,
            "tripId": "1322_9400_221210",
            "route": "S22",
            "routeType": 2,
            "bearing": null,
            "delay": 0,
            "inactive": false,
            "statePosition": "off_track",
            "vehicle": "9400"
        },
        "158": {
            "lat": 50.0324135,
            "lon": 15.2119007,
            "tripId": "1302_5871_221210",
            "route": "S2",
            "routeType": 2,
            "bearing": 185,
            "delay": 34,
            "inactive": false,
            "statePosition": "on_track",
            "vehicle": "5871"
        },
        "159": {
            "lat": 50.0643425,
            "lon": 14.297473,
            "tripId": "1365_11034_230312",
            "route": "S65",
            "routeType": 2,
            "bearing": 309,
            "delay": -22,
            "inactive": false,
            "statePosition": "at_stop",
            "vehicle": "11034"
        },
        "160": {
            "lat": 50.1495247,
            "lon": 14.5182543,
            "tripId": "1303_9520_221210",
            "route": "S3",
            "routeType": 2,
            "bearing": 309,
            "delay": 65,
            "inactive": false,
            "statePosition": "at_stop",
            "vehicle": "9520"
        },
        "161": {
            "lat": 50.12637,
            "lon": 14.6467371,
            "tripId": "1302_5851_221210",
            "route": "S2",
            "routeType": 2,
            "bearing": 64,
            "delay": -28,
            "inactive": false,
            "statePosition": "at_stop",
            "vehicle": "5851"
        },
        "162": {
            "lat": 50.00394,
            "lon": 14.4029922,
            "tripId": "1388_19001_221210",
            "route": "S88",
            "routeType": 2,
            "bearing": 168,
            "delay": 122,
            "inactive": false,
            "statePosition": "at_stop",
            "vehicle": "19001"
        },
        "163": {
            "lat": 50.1711426,
            "lon": 14.3957424,
            "tripId": "1304_9600_221210",
            "route": "S4",
            "routeType": 2,
            "bearing": 284,
            "delay": 15,
            "inactive": false,
            "statePosition": "on_track",
            "vehicle": "9600"
        },
        "164": {
            "lat": 49.9708939,
            "lon": 14.33192,
            "tripId": "1307_8800_221210",
            "route": "S7",
            "routeType": 2,
            "bearing": 210,
            "delay": 89,
            "inactive": false,
            "statePosition": "at_stop",
            "vehicle": "8800"
        },
        "165": {
            "lat": 50.08484,
            "lon": 14.6340723,
            "tripId": "1301_9301_221210",
            "route": "S1",
            "routeType": 2,
            "bearing": 84,
            "delay": 126,
            "inactive": false,
            "statePosition": "on_track",
            "vehicle": "9301"
        },
        "166": {
            "lat": 50.054924,
            "lon": 14.5373774,
            "tripId": "1309_2501_221210",
            "route": "S9",
            "routeType": 2,
            "bearing": 93,
            "delay": 452,
            "inactive": false,
            "statePosition": "on_track",
            "vehicle": "2501"
        },
        "167": {
            "lat": 50.03204,
            "lon": 14.3106976,
            "tripId": "1306_19930_221210",
            "route": "S6",
            "routeType": 2,
            "bearing": 285,
            "delay": -50,
            "inactive": false,
            "statePosition": "on_track",
            "vehicle": "19930"
        },
        "168": {
            "lat": 50.0976524,
            "lon": 14.3796329,
            "tripId": "1305_9850_230312",
            "route": "S5",
            "routeType": 2,
            "bearing": 253,
            "delay": 18,
            "inactive": false,
            "statePosition": "on_track",
            "vehicle": "9850"
        }
    }
}